{
  "method": "step1x_new",
  "generated_dir": "/scratch/aaa_exchange/AWARE/GENERATED_IMAGES/step1x_new",
  "original_dir": "/scratch/aaa_exchange/AWARE/FINAL_SPLITS/train/images",
  "target_dir": "/scratch/aaa_exchange/AWARE/AWACS/train",
  "manifest_path": "/scratch/aaa_exchange/AWARE/GENERATED_IMAGES/step1x_new/manifest.csv",
  "structure_type": "mixed",
  "task_type": "generation",
  "total_generated": 124981,
  "total_matched": 124981,
  "total_unmatched": 0,
  "overall_match_rate": 100.0,
  "domains": {
    "cloudy": {
      "total": 19976,
      "matched": 19976,
      "unmatched": 0,
      "match_rate": 100.0,
      "is_restoration": false,
      "restoration_source_weather": null,
      "datasets": {
        "ACDC": {
          "matched": 1402,
          "unmatched": 0,
          "total": 1402
        },
        "BDD100k": {
          "matched": 5548,
          "unmatched": 0,
          "total": 5548
        },
        "BDD10k": {
          "matched": 1561,
          "unmatched": 0,
          "total": 1561
        },
        "Cityscapes": {
          "matched": 997,
          "unmatched": 0,
          "total": 997
        },
        "IDD-AW": {
          "matched": 3492,
          "unmatched": 0,
          "total": 3492
        },
        "MapillaryVistas": {
          "matched": 3493,
          "unmatched": 0,
          "total": 3493
        },
        "OUTSIDE15k": {
          "matched": 3483,
          "unmatched": 0,
          "total": 3483
        }
      }
    },
    "dawn_dusk": {
      "total": 20488,
      "matched": 20488,
      "unmatched": 0,
      "match_rate": 100.0,
      "is_restoration": false,
      "restoration_source_weather": null,
      "datasets": {
        "ACDC": {
          "matched": 1402,
          "unmatched": 0,
          "total": 1402
        },
        "BDD100k": {
          "matched": 5549,
          "unmatched": 0,
          "total": 5549
        },
        "BDD10k": {
          "matched": 1561,
          "unmatched": 0,
          "total": 1561
        },
        "Cityscapes": {
          "matched": 1508,
          "unmatched": 0,
          "total": 1508
        },
        "IDD-AW": {
          "matched": 3492,
          "unmatched": 0,
          "total": 3492
        },
        "MapillaryVistas": {
          "matched": 3493,
          "unmatched": 0,
          "total": 3493
        },
        "OUTSIDE15k": {
          "matched": 3483,
          "unmatched": 0,
          "total": 3483
        }
      }
    },
    "foggy": {
      "total": 20628,
      "matched": 20628,
      "unmatched": 0,
      "match_rate": 100.0,
      "is_restoration": false,
      "restoration_source_weather": null,
      "datasets": {
        "ACDC": {
          "matched": 1401,
          "unmatched": 0,
          "total": 1401
        },
        "BDD100k": {
          "matched": 5550,
          "unmatched": 0,
          "total": 5550
        },
        "BDD10k": {
          "matched": 1560,
          "unmatched": 0,
          "total": 1560
        },
        "Cityscapes": {
          "matched": 1647,
          "unmatched": 0,
          "total": 1647
        },
        "IDD-AW": {
          "matched": 3492,
          "unmatched": 0,
          "total": 3492
        },
        "MapillaryVistas": {
          "matched": 3494,
          "unmatched": 0,
          "total": 3494
        },
        "OUTSIDE15k": {
          "matched": 3484,
          "unmatched": 0,
          "total": 3484
        }
      }
    },
    "night": {
      "total": 21025,
      "matched": 21025,
      "unmatched": 0,
      "match_rate": 100.0,
      "is_restoration": false,
      "restoration_source_weather": null,
      "datasets": {
        "ACDC": {
          "matched": 1402,
          "unmatched": 0,
          "total": 1402
        },
        "BDD100k": {
          "matched": 5549,
          "unmatched": 0,
          "total": 5549
        },
        "BDD10k": {
          "matched": 1561,
          "unmatched": 0,
          "total": 1561
        },
        "Cityscapes": {
          "matched": 2045,
          "unmatched": 0,
          "total": 2045
        },
        "IDD-AW": {
          "matched": 3492,
          "unmatched": 0,
          "total": 3492
        },
        "MapillaryVistas": {
          "matched": 3493,
          "unmatched": 0,
          "total": 3493
        },
        "OUTSIDE15k": {
          "matched": 3483,
          "unmatched": 0,
          "total": 3483
        }
      }
    },
    "rainy": {
      "total": 21050,
      "matched": 21050,
      "unmatched": 0,
      "match_rate": 100.0,
      "is_restoration": false,
      "restoration_source_weather": null,
      "datasets": {
        "ACDC": {
          "matched": 1402,
          "unmatched": 0,
          "total": 1402
        },
        "BDD100k": {
          "matched": 5549,
          "unmatched": 0,
          "total": 5549
        },
        "BDD10k": {
          "matched": 1561,
          "unmatched": 0,
          "total": 1561
        },
        "Cityscapes": {
          "matched": 2069,
          "unmatched": 0,
          "total": 2069
        },
        "IDD-AW": {
          "matched": 3492,
          "unmatched": 0,
          "total": 3492
        },
        "MapillaryVistas": {
          "matched": 3493,
          "unmatched": 0,
          "total": 3493
        },
        "OUTSIDE15k": {
          "matched": 3484,
          "unmatched": 0,
          "total": 3484
        }
      }
    },
    "snowy": {
      "total": 21814,
      "matched": 21814,
      "unmatched": 0,
      "match_rate": 100.0,
      "is_restoration": false,
      "restoration_source_weather": null,
      "datasets": {
        "ACDC": {
          "matched": 1402,
          "unmatched": 0,
          "total": 1402
        },
        "BDD100k": {
          "matched": 5550,
          "unmatched": 0,
          "total": 5550
        },
        "BDD10k": {
          "matched": 1561,
          "unmatched": 0,
          "total": 1561
        },
        "Cityscapes": {
          "matched": 2832,
          "unmatched": 0,
          "total": 2832
        },
        "IDD-AW": {
          "matched": 3492,
          "unmatched": 0,
          "total": 3492
        },
        "MapillaryVistas": {
          "matched": 3493,
          "unmatched": 0,
          "total": 3493
        },
        "OUTSIDE15k": {
          "matched": 3484,
          "unmatched": 0,
          "total": 3484
        }
      }
    }
  },
  "generated_at": "2026-02-07T22:50:45.003919"
}